splineops/__init__.py
splineops/_lsresize.cpython-312-darwin.so
splineops/differentials/differentials.py
splineops/differentials/__init__.py
splineops/utils/specs.py
splineops/utils/sphinx.py
splineops/utils/metrics.py
splineops/utils/diagram.py
splineops/utils/plotting.py
splineops/utils/__init__.py
splineops/utils/image.py
splineops/multiscale/pyramid.py
splineops/multiscale/__init__.py
splineops/multiscale/wavelets/spline_wavelets_tool.py
splineops/multiscale/wavelets/__init__.py
splineops/multiscale/wavelets/haar.py
splineops/multiscale/wavelets/abstract_wavelets.py
splineops/multiscale/wavelets/spline_filter.py
splineops/multiscale/wavelets/spline_wavelets.py
splineops/affine/affine.py
splineops/affine/__init__.py
splineops/resize/__init__.py
splineops/resize/resize.py
splineops/resize/_pycore/params.py
splineops/resize/_pycore/bspline.py
splineops/resize/_pycore/plan_1d.py
splineops/resize/_pycore/diff_integ.py
splineops/resize/_pycore/resize_1d.py
splineops/resize/_pycore/__init__.py
splineops/resize/_pycore/engine.py
splineops/resize/_pycore/utils.py
splineops/resize/_pycore/resize_nd.py
splineops/resize/_pycore/filters.py
splineops/smoothing_splines/__init__.py
splineops/smoothing_splines/fract_spline_auto_corr.py
splineops/smoothing_splines/fBm_per.py
splineops/smoothing_splines/smoothing_spline.py
splineops/adaptive_regression_splines/sparsification.py
splineops/adaptive_regression_splines/denoising.py
splineops/adaptive_regression_splines/__init__.py
splineops/spline_interpolation/__init__.py
splineops/spline_interpolation/utils.py
splineops/spline_interpolation/tensor_spline.py
splineops/spline_interpolation/modes/narrow_mirroring.py
splineops/spline_interpolation/modes/__init__.py
splineops/spline_interpolation/modes/extension_mode.py
splineops/spline_interpolation/modes/utils.py
splineops/spline_interpolation/modes/finite_support_coefficients.py
splineops/spline_interpolation/modes/periodic_padding.py
splineops-1.2.1.dist-info/RECORD
splineops-1.2.1.dist-info/WHEEL
splineops-1.2.1.dist-info/METADATA
splineops-1.2.1.dist-info/licenses/LICENSE
