Metadata-Version: 2.2
Name: splineops
Version: 1.2.1
Summary: Spline signal processing in N-D with support for GPU computing.
Author: Pablo Garcia-Amorena, Philippe Thévenaz, Arrate Muñoz Barrutia, Daniel Sage, Dimitris Perdios, Thomas Debarre, Michael Unser
License: BSD 3-Clause License
Classifier: Topic :: Scientific/Engineering :: Image Processing
Classifier: Topic :: Scientific/Engineering :: Mathematics
Classifier: Topic :: Software Development :: Libraries :: Python Modules
Classifier: Intended Audience :: Science/Research
Classifier: Intended Audience :: Developers
Classifier: Development Status :: 5 - Production/Stable
Classifier: License :: OSI Approved :: BSD License
Classifier: Programming Language :: Python :: 3.11
Classifier: Programming Language :: Python :: 3.12
Project-URL: Homepage, https://splineops.github.io/
Project-URL: Source, https://github.com/splineops/splineops
Project-URL: Issues, https://github.com/splineops/splineops/issues
Project-URL: Download, https://github.com/splineops/splineops.git
Requires-Python: >=3.11
Requires-Dist: numpy>=1.26
Requires-Dist: scipy>=1.15
Requires-Dist: matplotlib>=3.8
Provides-Extra: visualization
Requires-Dist: pooch>=1.8; extra == "visualization"
Requires-Dist: IPython>=8.26; extra == "visualization"
Provides-Extra: tests
Requires-Dist: tox>=4.13; extra == "tests"
Requires-Dist: pytest>=6.0; extra == "tests"
Provides-Extra: dev
Requires-Dist: splineops[tests,visualization]; extra == "dev"
Requires-Dist: black>=23.10; extra == "dev"
Requires-Dist: mypy>=1.8; extra == "dev"
Requires-Dist: build; extra == "dev"
Provides-Extra: dev-cupy
Requires-Dist: splineops[dev]; extra == "dev-cupy"
Requires-Dist: cupy>=12.2; extra == "dev-cupy"
Provides-Extra: docs
Requires-Dist: splineops[visualization]; extra == "docs"
Requires-Dist: sphinx>=7.3; extra == "docs"
Requires-Dist: sphinx-gallery>=0.17; extra == "docs"
Requires-Dist: sphinx-prompt>=1.8; extra == "docs"
Requires-Dist: sphinx-copybutton>=0.5; extra == "docs"
Requires-Dist: sphinx-remove-toctrees>=1.0; extra == "docs"
Requires-Dist: sphinx-design>=0.6; extra == "docs"
Requires-Dist: pydata-sphinx-theme>=0.15; extra == "docs"
Requires-Dist: myst-parser>=3.0; extra == "docs"
Requires-Dist: Pillow>=10.0; extra == "docs"
Requires-Dist: scikit-image>=0.25; extra == "docs"
Requires-Dist: opencv-python-headless>=4.8; extra == "docs"
Requires-Dist: torch>=2.0; extra == "docs"
Requires-Dist: imageio-ffmpeg>=0.5; extra == "docs"
